design.sv

module AXI_Lite_Slave (
  input wire ACLK,
  input wire ARESETn,
  
  //Write Address Channel
  input wire[3:0] AWADDR,
  input wire AWVALID,
  output reg AWREADY,
  
  //Write Data Channel
  input wire[31:0] WDATA,
  input wire[3:0] WSTRB,
  input wire WVALID,
  output reg WREADY,
  
  //Write Response Channel
  output reg[1:0] BRESP,
  output reg BVALID,
  input wire BREADY,
  
  //Read Address Channel
  input wire[3:0] ARADDR,
  input wire ARVALID,
  output reg ARREADY,
  
  //Read Data Channel
  output reg[31:0] RDATA,
  output reg[1:0] RRESP,
  output reg RVALID,
  input wire RREADY
);
  
  //State definitions
  localparam state_widle = 2'b00;
  localparam state_wdata = 2'b01;
  localparam state_wresp = 2'b10;
  localparam state_ridle = 1'b0;
  localparam state_rdata = 1'b1;
  
  //State register
  reg[1:0] wr_state;
  reg rd_state;

  //Internal registers
  reg[31:0] regx[3:0];
  
  //Internal address latch
  reg[3:0] wr_addr, rd_addr;
  
  //Write Channels
  always @(posedge ACLK) begin
    //Reset Condition
    if (!ARESETn) begin
      //Internal
      wr_addr <= 4'b0000;
      regx[0] <= 32'h0;
      regx[1] <= 32'h0;
      regx[2] <= 32'h0;
      regx[3] <= 32'h0;
      wr_state <= state_widle;
      
      //Write Channel
      AWREADY <= 0;
      WREADY  <= 0;
      BVALID  <= 0;
      BRESP   <= 2'b00;
    end
    
    else begin
      //Write FSM
      case(wr_state)
        state_widle: begin
          BVALID <= 1'b0;
          if(AWVALID && WVALID && (WSTRB != 4'b0000)) begin
            AWREADY <= 1'b1;
            WREADY <= 1'b1;
            wr_addr <= AWADDR;
            case (AWADDR[3:2])
              2'b00: begin
                if (WSTRB[0]) regx[0][7:0] <= WDATA[7:0];
                if (WSTRB[1]) regx[0][15:8] <= WDATA[15:8];
      			if (WSTRB[2]) regx[0][23:16] <= WDATA[23:16];
      			if (WSTRB[3]) regx[0][31:24] <= WDATA[31:24];
              end
              2'b01: begin
                if (WSTRB[0]) regx[1][7:0] <= WDATA[7:0];
                if (WSTRB[1]) regx[1][15:8] <= WDATA[15:8];
                if (WSTRB[2]) regx[1][23:16] <= WDATA[23:16];
                if (WSTRB[3]) regx[1][31:24] <= WDATA[31:24];
              end
              2'b10: begin
                if (WSTRB[0]) regx[2][7:0] <= WDATA[7:0];
                if (WSTRB[1]) regx[2][15:8] <= WDATA[15:8];
                if (WSTRB[2]) regx[2][23:16] <= WDATA[23:16];
                if (WSTRB[3]) regx[2][31:24] <= WDATA[31:24];
              end
              2'b11: begin
                if (WSTRB[0]) regx[3][7:0] <= WDATA[7:0];
                if (WSTRB[1]) regx[3][15:8] <= WDATA[15:8];
                if (WSTRB[2]) regx[3][23:16] <= WDATA[23:16];
                if (WSTRB[3]) regx[3][31:24] <= WDATA[31:24];
              end
              default: begin
              end
            endcase
            wr_state <= state_wresp;
          end
          else if(AWVALID) begin
            AWREADY <= 1'b1;
            wr_addr <= AWADDR;
            wr_state <= state_wdata;
          end
          else begin
            AWREADY <= 1'b0;
            WREADY <= 1'b0;
          end
        end
        
        state_wdata: begin
          AWREADY <= 1'b0;
          if (WVALID) begin
            WREADY <= 1'b1;
            if (WSTRB != 4'b0000) begin
              case (wr_addr[3:2])
                2'b00: begin
                  if (WSTRB[0]) regx[0][7:0] <= WDATA[7:0];
                  if (WSTRB[1]) regx[0][15:8] <= WDATA[15:8];
                  if (WSTRB[2]) regx[0][23:16] <= WDATA[23:16];
                  if (WSTRB[3]) regx[0][31:24] <= WDATA[31:24];
                end
                2'b01: begin
                  if (WSTRB[0]) regx[1][7:0] <= WDATA[7:0];
                  if (WSTRB[1]) regx[1][15:8] <= WDATA[15:8];
                  if (WSTRB[2]) regx[1][23:16] <= WDATA[23:16];
                  if (WSTRB[3]) regx[1][31:24] <= WDATA[31:24];
                end
                2'b10: begin
                  if (WSTRB[0]) regx[2][7:0] <= WDATA[7:0];
                  if (WSTRB[1]) regx[2][15:8] <= WDATA[15:8];
                  if (WSTRB[2]) regx[2][23:16] <= WDATA[23:16];
                  if (WSTRB[3]) regx[2][31:24] <= WDATA[31:24];
                end
                2'b11: begin
                  if (WSTRB[0]) regx[3][7:0] <= WDATA[7:0];
                  if (WSTRB[1]) regx[3][15:8] <= WDATA[15:8];
                  if (WSTRB[2]) regx[3][23:16] <= WDATA[23:16];
                  if (WSTRB[3]) regx[3][31:24] <= WDATA[31:24];
                end
                default: begin
                end
              endcase
            end
            wr_state <= state_wresp;
          end
          else begin
            WREADY <= 1'b0;
          end
        end
        
        state_wresp: begin
          WREADY <= 1'b0;
          BVALID <= 1'b1;
          
          if (wr_addr > 4'h0C || (wr_addr[1:0] != 2'b00)) begin
            BRESP <= 2'b10;
          end
          else begin
            BRESP <= 2'b00;
          end
          
          if (BREADY) begin
            wr_state <= state_widle;
          end
        end
        
        default: wr_state <= state_widle;
      endcase
    end
  end
  
  always @(posedge ACLK) begin
    //Reset Condition
    if (!ARESETn) begin
      //Internal
      rd_state <= state_ridle;
      rd_addr <= 4'b0000;
      
      //Read Channel
      ARREADY <= 0;
      RVALID  <= 0;
      RRESP   <= 2'b00;
      RDATA   <= 32'h0;
    end
    
    else begin
      //Read FSM
      case(rd_state)
        state_ridle: begin
          RVALID <= 1'b0;
          if (ARVALID) begin
            ARREADY <= 1'b1;
            rd_addr <= ARADDR;
            rd_state <= state_rdata;
          end
          else begin
            ARREADY <= 1'b0;
          end
        end
        
        state_rdata: begin
          if (rd_addr > 4'h0C || (rd_addr[1:0] != 2'b00)) begin
            RRESP <= 2'b10;
          end
          else begin
            RRESP <= 2'b00;
          end
        
          ARREADY <= 1'b0;
          case (rd_addr[3:2])
            2'b00: RDATA <= regx[0];
            2'b01: RDATA <= regx[1];
            2'b10: RDATA <= regx[2];
            2'b11: RDATA <= regx[3];
          endcase
          RVALID <= 1'b1;
        
          if (RREADY) begin
            rd_state <= state_ridle;
          end
        end
      
        default: rd_state <= state_ridle;
      endcase
    end
  end
endmodule

testbench.sv
`timescale 1ns / 1ps

module axi_lite_slave_tb;
  
  logic ACLK;
  logic ARESETn;
  
  logic [3:0] AWADDR;
  logic AWVALID;
  logic AWREADY;
  
  logic [31:0] WDATA;
  logic [3:0] WSTRB;
  logic WVALID;
  logic WREADY;
  
  logic [1:0] BRESP;
  logic BVALID;
  logic BREADY;
  
  logic [3:0] ARADDR;
  logic ARVALID;
  logic ARREADY;
  
  logic [31:0] RDATA;
  logic [1:0] RRESP;
  logic RVALID;
  logic RREADY;
  
  int error_count = 0;
  int test_count = 0;
  
  AXI_Lite_Slave dut (
    .ACLK(ACLK),
    .ARESETn(ARESETn),
    .AWADDR(AWADDR),
    .AWVALID(AWVALID),
    .AWREADY(AWREADY),
    .WDATA(WDATA),
    .WSTRB(WSTRB),
    .WVALID(WVALID),
    .WREADY(WREADY),
    .BRESP(BRESP),
    .BVALID(BVALID),
    .BREADY(BREADY),
    .ARADDR(ARADDR),
    .ARVALID(ARVALID),
    .ARREADY(ARREADY),
    .RDATA(RDATA),
    .RRESP(RRESP),
    .RVALID(RVALID),
    .RREADY(RREADY)
  );
  
  initial begin
    ACLK = 0;
    forever #5 ACLK = ~ACLK;
  end
  
  task automatic reset_sequence();
    ARESETn = 0;
    AWADDR = 0;
    AWVALID = 0;
    WDATA = 0;
    WSTRB = 0;
    WVALID = 0;
    BREADY = 0;
    ARADDR = 0;
    ARVALID = 0;
    RREADY = 0;
    repeat(5) @(posedge ACLK);
    ARESETn = 1;
    repeat(2) @(posedge ACLK);
    $display("[%0t] reset done", $time);
  endtask
  
  task automatic axi_write_simul(
    input logic [3:0] addr,
    input logic [31:0] data,
    input logic [3:0] strb,
    output logic [1:0] resp
  );
    test_count++;
    
    @(posedge ACLK);
    AWADDR = addr;
    AWVALID = 1;
    WDATA = data;
    WSTRB = strb;
    WVALID = 1;
    BREADY = 1;
    
    wait(AWREADY && AWVALID);
    @(posedge ACLK);
    AWVALID = 0;
    
    wait(WREADY && WVALID);
    @(posedge ACLK);
    WVALID = 0;
    
    wait(BVALID && BREADY);
    @(posedge ACLK);
    resp = BRESP;
    BREADY = 0;
    
    @(posedge ACLK);
  endtask
  
  task automatic axi_write_separate(
    input logic [3:0] addr,
    input logic [31:0] data,
    input logic [3:0] strb,
    output logic [1:0] resp
  );
    test_count++;
    
    @(posedge ACLK);
    AWADDR = addr;
    AWVALID = 1;
    BREADY = 1;
    
    wait(AWREADY);
    @(posedge ACLK);
    AWVALID = 0;
    
    @(posedge ACLK);
    WDATA = data;
    WSTRB = strb;
    WVALID = 1;
    
    wait(WREADY);
    @(posedge ACLK);
    WVALID = 0;
    
    wait(BVALID);
    @(posedge ACLK);
    resp = BRESP;
    BREADY = 0;
    
    @(posedge ACLK);
  endtask
  
  task automatic axi_read(
    input logic [3:0] addr,
    output logic [31:0] data,
    output logic [1:0] resp
  );
    test_count++;
    
    @(posedge ACLK);
    ARADDR = addr;
    ARVALID = 1;
    RREADY = 1;
    
    wait(ARREADY);
    @(posedge ACLK);
    ARVALID = 0;
    
    wait(RVALID);
    @(posedge ACLK);
    data = RDATA;
    resp = RRESP;
    RREADY = 0;
    
    @(posedge ACLK);
  endtask
  
  task automatic check_data(
    input logic [31:0] expected,
    input logic [31:0] actual,
    input string msg
  );
    if (expected !== actual) begin
      $display("FAIL: %s (exp=0x%08h, got=0x%08h)", msg, expected, actual);
      error_count++;
    end else begin
      $display("pass: %s", msg);
    end
  endtask
  
  task automatic check_resp(
    input logic [1:0] expected,
    input logic [1:0] actual,
    input string msg
  );
    if (expected !== actual) begin
      $display("FAIL: %s (exp=%0d, got=%0d)", msg, expected, actual);
      error_count++;
    end
  endtask
  
  initial begin
    logic [31:0] read_data;
    logic [1:0] resp;
    
    reset_sequence();
    
    $display("\nbasic write/read");
    axi_write_simul(4'h0, 32'hDEF11ACE, 4'hF, resp);
    check_resp(2'b00, resp, "wr reg0");
    axi_read(4'h0, read_data, resp);
    check_resp(2'b00, resp, "rd reg0");
    check_data(32'hDEF11ACE, read_data, "reg0 data");
    
    $display("\nwrite all regs");
    axi_write_simul(4'h0, 32'h12345678, 4'hF, resp);
    axi_write_simul(4'h4, 32'h9ABCDEF0, 4'hF, resp);
    axi_write_simul(4'h8, 32'hFEDCBA98, 4'hF, resp);
    axi_write_simul(4'hC, 32'h76543210, 4'hF, resp);
    
    axi_read(4'h0, read_data, resp);
    check_data(32'h12345678, read_data, "reg0");
    axi_read(4'h4, read_data, resp);
    check_data(32'h9ABCDEF0, read_data, "reg1");
    axi_read(4'h8, read_data, resp);
    check_data(32'hFEDCBA98, read_data, "reg2");
    axi_read(4'hC, read_data, resp);
    check_data(32'h76543210, read_data, "reg3");
    
    $display("\nseparate addr/data");
    axi_write_separate(4'h0, 32'hAAAAAAAA, 4'hF, resp);
    check_resp(2'b00, resp, "sep wr");
    axi_read(4'h0, read_data, resp);
    check_data(32'hAAAAAAAA, read_data, "reg0 sep");
    
    $display("\nbyte strobes");
    axi_write_simul(4'h0, 32'h00000000, 4'hF, resp);
    
    axi_write_simul(4'h0, 32'h000000AB, 4'h1, resp);
    axi_read(4'h0, read_data, resp);
    check_data(32'h000000AB, read_data, "strb[0]");
    
    axi_write_simul(4'h0, 32'h0000CD00, 4'h2, resp);
    axi_read(4'h0, read_data, resp);
    check_data(32'h0000CDAB, read_data, "strb[1]");
    
    axi_write_simul(4'h0, 32'h00EF0000, 4'h4, resp);
    axi_read(4'h0, read_data, resp);
    check_data(32'h00EFCDAB, read_data, "strb[2]");
    
    axi_write_simul(4'h0, 32'h12000000, 4'h8, resp);
    axi_read(4'h0, read_data, resp);
    check_data(32'h12EFCDAB, read_data, "strb[3]");
    
    axi_write_simul(4'h4, 32'h00000000, 4'hF, resp);
    axi_write_simul(4'h4, 32'h00AA00BB, 4'h5, resp);
    axi_read(4'h4, read_data, resp);
    check_data(32'h00AA00BB, read_data, "strb[0,2]");
    
    $display("\nunaligned addr");
    axi_write_simul(4'h1, 32'hBADBAD01, 4'hF, resp);
    check_resp(2'b10, resp, "wr 0x1");
    axi_write_simul(4'h2, 32'hBADBAD02, 4'hF, resp);
    check_resp(2'b10, resp, "wr 0x2");
    axi_write_simul(4'h3, 32'hBADBAD03, 4'hF, resp);
    check_resp(2'b10, resp, "wr 0x3");
    
    axi_read(4'h1, read_data, resp);
    check_resp(2'b10, resp, "rd 0x1");
    axi_read(4'h5, read_data, resp);
    check_resp(2'b10, resp, "rd 0x5");
    
    $display("\nout of range");
    axi_write_simul(4'hD, 32'hBADBAD0D, 4'hF, resp);
    check_resp(2'b10, resp, "wr 0xD");
    axi_write_simul(4'hE, 32'hBADBAD0E, 4'hF, resp);
    check_resp(2'b10, resp, "wr 0xE");
    axi_read(4'hF, read_data, resp);
    check_resp(2'b10, resp, "rd 0xF");
    
    $display("\nwstrb=0");
    axi_write_simul(4'h0, 32'hFFFFFFFF, 4'hF, resp);
    axi_read(4'h0, read_data, resp);
    check_data(32'hFFFFFFFF, read_data, "init");
    
    axi_write_simul(4'h0, 32'h00000000, 4'h0, resp);
    check_resp(2'b00, resp, "wstrb=0");
    axi_read(4'h0, read_data, resp);
    check_data(32'hFFFFFFFF, read_data, "unchanged");
    
    axi_write_separate(4'h4, 32'h11111111, 4'h0, resp);
    check_resp(2'b00, resp, "wstrb=0 sep");
    
    $display("\nback-to-back");
    for (int i = 0; i < 4; i++) begin
      axi_write_simul(i*4, 32'h11111111 * (i+1), 4'hF, resp);
    end
    for (int i = 0; i < 4; i++) begin
      axi_read(i*4, read_data, resp);
      check_data(32'h11111111 * (i+1), read_data, $sformatf("reg%0d", i));
    end
    
    $display("\nreset during op");
    axi_write_simul(4'h0, 32'hDEADBEEF, 4'hF, resp);
    axi_write_simul(4'h4, 32'hCAFEBABE, 4'hF, resp);
    
    reset_sequence();
    
    axi_read(4'h0, read_data, resp);
    check_data(32'h00000000, read_data, "reg0 post-rst");
    axi_read(4'h4, read_data, resp);
    check_data(32'h00000000, read_data, "reg1 post-rst");
    axi_read(4'h8, read_data, resp);
    check_data(32'h00000000, read_data, "reg2 post-rst");
    axi_read(4'hC, read_data, resp);
    check_data(32'h00000000, read_data, "reg3 post-rst");
    
    $display("\nmixed rd/wr");
    axi_write_simul(4'h0, 32'hA5A5A5A5, 4'hF, resp);
    axi_read(4'h0, read_data, resp);
    check_data(32'hA5A5A5A5, read_data, "wr-rd");
    
    axi_write_simul(4'h4, 32'h5A5A5A5A, 4'hF, resp);
    axi_read(4'h0, read_data, resp);
    check_data(32'hA5A5A5A5, read_data, "reg0 no change");
    axi_read(4'h4, read_data, resp);
    check_data(32'h5A5A5A5A, read_data, "reg1 ok");
    
    repeat(10) @(posedge ACLK);
    
    $display("\ntests: %0d", test_count);
    $display("errors: %0d", error_count);
    if (error_count == 0)
      $display("all pass");
    else
      $display("failed");
    
    $finish;
  end
  
  initial begin
    #100000;
    $display("\ntimeout");
    $finish;
  end
  
  initial begin
    $dumpfile("axi_lite_slave_tb.vcd");
    $dumpvars(0, axi_lite_slave_tb);
  end

endmodule

axi_lite_slave_tb.vcd
$date
	Thu Oct 30 01:49:00 2025
$end
$version
	Icarus Verilog
$end
$timescale
	1ps
$end
$scope module axi_lite_slave_tb $end
$var wire 1 ! WREADY $end
$var wire 1 " RVALID $end
$var wire 2 # RRESP [1:0] $end
$var wire 32 $ RDATA [31:0] $end
$var wire 1 % BVALID $end
$var wire 2 & BRESP [1:0] $end
$var wire 1 ' AWREADY $end
$var wire 1 ( ARREADY $end
$var reg 1 ) ACLK $end
$var reg 4 * ARADDR [3:0] $end
$var reg 1 + ARESETn $end
$var reg 1 , ARVALID $end
$var reg 4 - AWADDR [3:0] $end
$var reg 1 . AWVALID $end
$var reg 1 / BREADY $end
$var reg 1 0 RREADY $end
$var reg 32 1 WDATA [31:0] $end
$var reg 4 2 WSTRB [3:0] $end
$var reg 1 3 WVALID $end
$var integer 32 4 error_count [31:0] $end
$var integer 32 5 test_count [31:0] $end
$scope module dut $end
$var wire 1 ) ACLK $end
$var wire 4 6 ARADDR [3:0] $end
$var wire 1 + ARESETn $end
$var wire 1 , ARVALID $end
$var wire 4 7 AWADDR [3:0] $end
$var wire 1 . AWVALID $end
$var wire 1 / BREADY $end
$var wire 1 0 RREADY $end
$var wire 32 8 WDATA [31:0] $end
$var wire 4 9 WSTRB [3:0] $end
$var wire 1 3 WVALID $end
$var parameter 1 : state_rdata $end
$var parameter 1 ; state_ridle $end
$var parameter 2 < state_wdata $end
$var parameter 2 = state_widle $end
$var parameter 2 > state_wresp $end
$var reg 1 ( ARREADY $end
$var reg 1 ' AWREADY $end
$var reg 2 ? BRESP [1:0] $end
$var reg 1 % BVALID $end
$var reg 32 @ RDATA [31:0] $end
$var reg 2 A RRESP [1:0] $end
$var reg 1 " RVALID $end
$var reg 1 ! WREADY $end
$var reg 4 B rd_addr [3:0] $end
$var reg 1 C rd_state $end
$var reg 4 D wr_addr [3:0] $end
$var reg 2 E wr_state [1:0] $end
$upscope $end
$scope begin $unm_blk_40 $end
$var reg 32 F read_data [31:0] $end
$var reg 2 G resp [1:0] $end
$scope begin $ivl_for_loop0 $end
$var integer 32 H i [31:0] $end
$upscope $end
$scope begin $ivl_for_loop1 $end
$var integer 32 I i [31:0] $end
$upscope $end
$upscope $end
$scope task axi_read $end
$upscope $end
$scope task axi_write_separate $end
$upscope $end
$scope task axi_write_simul $end
$upscope $end
$scope task check_data $end
$upscope $end
$scope task check_resp $end
$upscope $end
$scope task reset_sequence $end
$upscope $end
$upscope $end
$enddefinitions $end
$comment Show the parameter values. $end
$dumpall
b10 >
b0 =
b1 <
0;
1:
$end
#0
$dumpvars
b0 I
b0 H
bx G
bx F
bx E
bx D
xC
bx B
bx A
bx @
bx ?
b0 9
b0 8
b0 7
b0 6
b0 5
b0 4
03
b0 2
b0 1
00
0/
0.
b0 -
0,
0+
b0 *
0)
x(
x'
bx &
x%
bx $
bx #
x"
x!
$end
#5000
b0 &
b0 ?
0%
0!
0'
b0 E
b0 D
b0 $
b0 @
b0 #
b0 A
0"
0(
b0 B
0C
1)
#10000
0)
#15000
1)
#20000
0)
#25000
1)
#30000
0)
#35000
1)
#40000
0)
#45000
1+
1)
#50000
0)
#55000
1)
#60000
0)
#65000
b1 5
1)
#70000
0)
#75000
b10 E
1!
1'
1/
13
b1111 2
b1111 9
b11011110111100010001101011001110 1
b11011110111100010001101011001110 8
1.
1)
#80000
0)
#85000
b0 E
1%
0!
0.
1)
#90000
0)
#95000
0'
0%
03
1)
#100000
0)
#105000
0/
1)
#110000
0)
#115000
b10 5
b0 G
1)
#120000
0)
#125000
1C
1(
10
1,
1)
#130000
0)
#135000
0C
1"
b11011110111100010001101011001110 $
b11011110111100010001101011001110 @
0(
0,
1)
#140000
0)
#145000
0"
00
1)
#150000
0)
#155000
b11 5
b11011110111100010001101011001110 F
1)
#160000
0)
#165000
b10 E
1!
1'
1/
13
b10010001101000101011001111000 1
b10010001101000101011001111000 8
1.
1)
#170000
0)
#175000
b0 E
1%
0!
0.
1)
#180000
0)
#185000
0'
0%
03
1)
#190000
0)
#195000
0/
1)
#200000
0)
#205000
b100 5
1)
#210000
0)
#215000
b10 E
b100 D
1!
1'
1/
13
b10011010101111001101111011110000 1
b10011010101111001101111011110000 8
1.
b100 -
b100 7
1)
#220000
0)
#225000
b0 E
1%
0!
0.
1)
#230000
0)
#235000
0'
0%
03
1)
#240000
0)
#245000
0/
1)
#250000
0)
#255000
b101 5
1)
#260000
0)
#265000
b10 E
b1000 D
1!
1'
1/
13
b11111110110111001011101010011000 1
b11111110110111001011101010011000 8
1.
b1000 -
b1000 7
1)
#270000
0)
#275000
b0 E
1%
0!
0.
1)
#280000
0)
#285000
0'
0%
03
1)
#290000
0)
#295000
0/
1)
#300000
0)
#305000
b110 5
1)
#310000
0)
#315000
b10 E
b1100 D
1!
1'
1/
13
b1110110010101000011001000010000 1
b1110110010101000011001000010000 8
1.
b1100 -
b1100 7
1)
#320000
0)
#325000
b0 E
1%
0!
0.
1)
#330000
0)
#335000
0'
0%
03
1)
#340000
0)
#345000
0/
1)
#350000
0)
#355000
b111 5
1)
#360000
0)
#365000
1C
1(
10
1,
1)
#370000
0)
#375000
0C
1"
b10010001101000101011001111000 $
b10010001101000101011001111000 @
0(
0,
1)
#380000
0)
#385000
0"
00
1)
#390000
0)
#395000
b1000 5
b10010001101000101011001111000 F
1)
#400000
0)
#405000
1C
b100 B
1(
10
1,
b100 *
b100 6
1)
#410000
0)
#415000
0C
1"
b10011010101111001101111011110000 $
b10011010101111001101111011110000 @
0(
0,
1)
#420000
0)
#425000
0"
00
1)
#430000
0)
#435000
b1001 5
b10011010101111001101111011110000 F
1)
#440000
0)
#445000
1C
b1000 B
1(
10
1,
b1000 *
b1000 6
1)
#450000
0)
#455000
0C
1"
b11111110110111001011101010011000 $
b11111110110111001011101010011000 @
0(
0,
1)
#460000
0)
#465000
0"
00
1)
#470000
0)
#475000
b1010 5
b11111110110111001011101010011000 F
1)
#480000
0)
#485000
1C
b1100 B
1(
10
1,
b1100 *
b1100 6
1)
#490000
0)
#495000
0C
1"
b1110110010101000011001000010000 $
b1110110010101000011001000010000 @
0(
0,
1)
#500000
0)
#505000
0"
00
1)
#510000
0)
#515000
b1011 5
b1110110010101000011001000010000 F
1)
#520000
0)
#525000
b1 E
b0 D
1'
1/
1.
b0 -
b0 7
1)
#530000
0)
#535000
0'
0.
1)
#540000
0)
#545000
13
b10101010101010101010101010101010 1
b10101010101010101010101010101010 8
1)
#550000
0)
#555000
b10 E
1!
1)
#560000
0)
#565000
b0 E
1%
0!
03
1)
#570000
0)
#575000
0%
0/
1)
#580000
0)
#585000
b1100 5
1)
#590000
0)
#595000
1C
b0 B
1(
10
1,
b0 *
b0 6
1)
#600000
0)
#605000
0C
1"
b10101010101010101010101010101010 $
b10101010101010101010101010101010 @
0(
0,
1)
#610000
0)
#615000
0"
00
1)
#620000
0)
#625000
b1101 5
b10101010101010101010101010101010 F
1)
#630000
0)
#635000
b10 E
1!
1'
1/
13
b0 1
b0 8
1.
1)
#640000
0)
#645000
b0 E
1%
0!
0.
1)
#650000
0)
#655000
0'
0%
03
1)
#660000
0)
#665000
0/
1)
#670000
0)
#675000
b1110 5
1)
#680000
0)
#685000
b10 E
1!
1'
1/
13
b1 2
b1 9
b10101011 1
b10101011 8
1.
1)
#690000
0)
#695000
b0 E
1%
0!
0.
1)
#700000
0)
#705000
0'
0%
03
1)
#710000
0)
#715000
0/
1)
#720000
0)
#725000
b1111 5
1)
#730000
0)
#735000
1C
1(
10
1,
1)
#740000
0)
#745000
0C
1"
b10101011 $
b10101011 @
0(
0,
1)
#750000
0)
#755000
0"
00
1)
#760000
0)
#765000
b10000 5
b10101011 F
1)
#770000
0)
#775000
b10 E
1!
1'
1/
13
b10 2
b10 9
b1100110100000000 1
b1100110100000000 8
1.
1)
#780000
0)
#785000
b0 E
1%
0!
0.
1)
#790000
0)
#795000
0'
0%
03
1)
#800000
0)
#805000
0/
1)
#810000
0)
#815000
b10001 5
1)
#820000
0)
#825000
1C
1(
10
1,
1)
#830000
0)
#835000
0C
1"
b1100110110101011 $
b1100110110101011 @
0(
0,
1)
#840000
0)
#845000
0"
00
1)
#850000
0)
#855000
b10010 5
b1100110110101011 F
1)
#860000
0)
#865000
b10 E
1!
1'
1/
13
b100 2
b100 9
b111011110000000000000000 1
b111011110000000000000000 8
1.
1)
#870000
0)
#875000
b0 E
1%
0!
0.
1)
#880000
0)
#885000
0'
0%
03
1)
#890000
0)
#895000
0/
1)
#900000
0)
#905000
b10011 5
1)
#910000
0)
#915000
1C
1(
10
1,
1)
#920000
0)
#925000
0C
1"
b111011111100110110101011 $
b111011111100110110101011 @
0(
0,
1)
#930000
0)
#935000
0"
00
1)
#940000
0)
#945000
b10100 5
b111011111100110110101011 F
1)
#950000
0)
#955000
b10 E
1!
1'
1/
13
b1000 2
b1000 9
b10010000000000000000000000000 1
b10010000000000000000000000000 8
1.
1)
#960000
0)
#965000
b0 E
1%
0!
0.
1)
#970000
0)
#975000
0'
0%
03
1)
#980000
0)
#985000
0/
1)
#990000
0)
#995000
b10101 5
1)
#1000000
0)
#1005000
1C
1(
10
1,
1)
#1010000
0)
#1015000
0C
1"
b10010111011111100110110101011 $
b10010111011111100110110101011 @
0(
0,
1)
#1020000
0)
#1025000
0"
00
1)
#1030000
0)
#1035000
b10110 5
b10010111011111100110110101011 F
1)
#1040000
0)
#1045000
b10 E
b100 D
1!
1'
1/
13
b1111 2
b1111 9
b0 1
b0 8
1.
b100 -
b100 7
1)
#1050000
0)
#1055000
b0 E
1%
0!
0.
1)
#1060000
0)
#1065000
0'
0%
03
1)
#1070000
0)
#1075000
0/
1)
#1080000
0)
#1085000
b10111 5
1)
#1090000
0)
#1095000
b10 E
1!
1'
1/
13
b101 2
b101 9
b101010100000000010111011 1
b101010100000000010111011 8
1.
1)
#1100000
0)
#1105000
b0 E
1%
0!
0.
1)
#1110000
0)
#1115000
0'
0%
03
1)
#1120000
0)
#1125000
0/
1)
#1130000
0)
#1135000
b11000 5
1)
#1140000
0)
#1145000
1C
b100 B
1(
10
1,
b100 *
b100 6
1)
#1150000
0)
#1155000
0C
1"
b101010100000000010111011 $
b101010100000000010111011 @
0(
0,
1)
#1160000
0)
#1165000
0"
00
1)
#1170000
0)
#1175000
b11001 5
b101010100000000010111011 F
1)
#1180000
0)
#1185000
b10 E
b1 D
1!
1'
1/
13
b1111 2
b1111 9
b10111010110110111010110100000001 1
b10111010110110111010110100000001 8
1.
b1 -
b1 7
1)
#1190000
0)
#1195000
b0 E
b10 &
b10 ?
1%
0!
0.
1)
#1200000
0)
#1205000
0'
0%
03
1)
#1210000
0)
#1215000
0/
1)
#1220000
0)
#1225000
b11010 5
b10 G
1)
#1230000
0)
#1235000
b10 E
b10 D
1!
1'
1/
13
b10111010110110111010110100000010 1
b10111010110110111010110100000010 8
1.
b10 -
b10 7
1)
#1240000
0)
#1245000
b0 E
1%
0!
0.
1)
#1250000
0)
#1255000
0'
0%
03
1)
#1260000
0)
#1265000
0/
1)
#1270000
0)
#1275000
b11011 5
1)
#1280000
0)
#1285000
b10 E
b11 D
1!
1'
1/
13
b10111010110110111010110100000011 1
b10111010110110111010110100000011 8
1.
b11 -
b11 7
1)
#1290000
0)
#1295000
b0 E
1%
0!
0.
1)
#1300000
0)
#1305000
0'
0%
03
1)
#1310000
0)
#1315000
0/
1)
#1320000
0)
#1325000
b11100 5
1)
#1330000
0)
#1335000
1C
b1 B
1(
10
1,
b1 *
b1 6
1)
#1340000
0)
#1345000
0C
1"
b10111010110110111010110100000011 $
b10111010110110111010110100000011 @
0(
b10 #
b10 A
0,
1)
#1350000
0)
#1355000
0"
00
1)
#1360000
0)
#1365000
b11101 5
b10111010110110111010110100000011 F
1)
#1370000
0)
#1375000
1C
b101 B
1(
10
1,
b101 *
b101 6
1)
#1380000
0)
#1385000
0C
1"
b101010100000000010111011 $
b101010100000000010111011 @
0(
0,
1)
#1390000
0)
#1395000
0"
00
1)
#1400000
0)
#1405000
b11110 5
b101010100000000010111011 F
1)
#1410000
0)
#1415000
b10 E
b1101 D
1!
1'
1/
13
b10111010110110111010110100001101 1
b10111010110110111010110100001101 8
1.
b1101 -
b1101 7
1)
#1420000
0)
#1425000
b0 E
1%
0!
0.
1)
#1430000
0)
#1435000
0'
0%
03
1)
#1440000
0)
#1445000
0/
1)
#1450000
0)
#1455000
b11111 5
1)
#1460000
0)
#1465000
b10 E
b1110 D
1!
1'
1/
13
b10111010110110111010110100001110 1
b10111010110110111010110100001110 8
1.
b1110 -
b1110 7
1)
#1470000
0)
#1475000
b0 E
1%
0!
0.
1)
#1480000
0)
#1485000
0'
0%
03
1)
#1490000
0)
#1495000
0/
1)
#1500000
0)
#1505000
b100000 5
1)
#1510000
0)
#1515000
1C
b1111 B
1(
10
1,
b1111 *
b1111 6
1)
#1520000
0)
#1525000
0C
1"
b10111010110110111010110100001110 $
b10111010110110111010110100001110 @
0(
0,
1)
#1530000
0)
#1535000
0"
00
1)
#1540000
0)
#1545000
b100001 5
b10111010110110111010110100001110 F
1)
#1550000
0)
#1555000
b10 E
b0 D
1!
1'
1/
13
b11111111111111111111111111111111 1
b11111111111111111111111111111111 8
1.
b0 -
b0 7
1)
#1560000
0)
#1565000
b0 E
b0 &
b0 ?
1%
0!
0.
1)
#1570000
0)
#1575000
0'
0%
03
1)
#1580000
0)
#1585000
0/
1)
#1590000
0)
#1595000
b100010 5
b0 G
1)
#1600000
0)
#1605000
1C
b0 B
1(
10
1,
b0 *
b0 6
1)
#1610000
0)
#1615000
0C
1"
b11111111111111111111111111111111 $
b11111111111111111111111111111111 @
0(
b0 #
b0 A
0,
1)
#1620000
0)
#1625000
0"
00
1)
#1630000
0)
#1635000
b100011 5
b11111111111111111111111111111111 F
1)
#1640000
0)
#1645000
b1 E
1'
1/
13
b0 2
b0 9
b0 1
b0 8
1.
1)
#1650000
0)
#1655000
b10 E
1!
0'
0.
1)
#1660000
0)
#1665000
b0 E
1%
0!
03
1)
#1670000
0)
#1675000
0%
0/
1)
#1680000
0)
#1685000
b100100 5
1)
#1690000
0)
#1695000
1C
1(
10
1,
1)
#1700000
0)
#1705000
0C
1"
0(
0,
1)
#1710000
0)
#1715000
0"
00
1)
#1720000
0)
#1725000
b100101 5
1)
#1730000
0)
#1735000
b1 E
b100 D
1'
1/
1.
b100 -
b100 7
1)
#1740000
0)
#1745000
0'
0.
1)
#1750000
0)
#1755000
13
b10001000100010001000100010001 1
b10001000100010001000100010001 8
1)
#1760000
0)
#1765000
b10 E
1!
1)
#1770000
0)
#1775000
b0 E
1%
0!
03
1)
#1780000
0)
#1785000
0%
0/
1)
#1790000
0)
